flask_roles/__init__.py
flask_roles/model.py
flask_roles-0.3.dist-info/LICENSE
flask_roles-0.3.dist-info/METADATA
flask_roles-0.3.dist-info/WHEEL
flask_roles-0.3.dist-info/top_level.txt
flask_roles-0.3.dist-info/RECORD
