Metadata-Version: 2.1
Name: flask-roles
Version: 0.3
Summary: Flask plugin to add roles to a project
Home-page: https://github.com/labeneator/flask-roles
Author: Laban Mwangi
Author-email: support@east36.co.ke
License: GPLv3
Platform: any
Classifier: Development Status :: 4 - Beta
Classifier: Environment :: Web Environment
Classifier: Intended Audience :: Developers
Classifier: License :: OSI Approved :: BSD License
Classifier: Operating System :: OS Independent
Classifier: Programming Language :: Python
Classifier: Topic :: Internet :: WWW/HTTP :: Dynamic Content
Classifier: Topic :: Software Development :: Libraries :: Python Modules
Requires-Dist: Flask-Login (>=0.5.0)
Requires-Dist: Flask-Principal (>=0.4.0)
Provides-Extra: testing
Requires-Dist: pip-tools (==4.5.1) ; extra == 'testing'
Requires-Dist: mccabe ; extra == 'testing'
Requires-Dist: pytest-cov ; extra == 'testing'
Requires-Dist: pytest ; extra == 'testing'
